README.rst
setup.py
dew/__init__.py
dew/__main__.py
dew/args.py
dew/cli.py
dew/command.py
dew/dependencygraph.py
dew/dependencyprocessor.py
dew/depstate.py
dew/dewfile.py
dew/exceptions.py
dew/git.py
dew/impl.py
dew/lockfile.py
dew/projectprocessor.py
dew/projectproperties.py
dew/storage.py
dew/subprocesscaller.py
dew/view.py
dew/builder/__init__.py
dew/builder/cmake.py
dew/builder/makefile.py
dew/builder/xcode.py
dew/commands/__init__.py
dew/commands/bootstrap.py
dew/commands/build.py
dew/commands/clean.py
dew/commands/finish.py
dew/commands/update.py
dew/commands/upgrade.py
dew/commands/workon.py
dew/data/cmake/dew.cmake
dew/remote/__init__.py
dew/remote/git.py
dew/remote/local.py
dew_pacman.egg-info/PKG-INFO
dew_pacman.egg-info/SOURCES.txt
dew_pacman.egg-info/dependency_links.txt
dew_pacman.egg-info/entry_points.txt
dew_pacman.egg-info/requires.txt
dew_pacman.egg-info/top_level.txt