Metadata-Version: 1.1
Name: dew-pacman
Version: 0.10.0
Summary: Development Environment Wrangler
Home-page: https://github.com/sfuller/dew
Author: Sam Fuller
Author-email: sam@samfullerstudios.com
License: Apache
Keywords: development build-tools dependencies package-manager c c++ cmake
Platform: UNKNOWN
Classifier: Development Status :: 3 - Alpha
Classifier: Intended Audience :: Developers
Classifier: Topic :: Software Development :: Build Tools
Classifier: License :: OSI Approved :: Apache Software License
Classifier: Programming Language :: Python :: 3
Classifier: Programming Language :: Python :: 3 :: Only
Classifier: Programming Language :: Python :: 3.6
